audio_miner/__init__.py
audio_miner/audio_transcriber.py
audio_miner/cli.py
audio_miner/main.py
audio_miner/version.py
test/__init__.py
test/test_audio_transcriber.py
test/test_edge_cases.py
test/test_file_monitor.py
test/test_full_cycle.py
test/test_logging.py
test/test_radiorecoder.py
test/test_record_transcribe_flags.py
test/test_recorder.py
audio_miner-0.0.6.dist-info/LICENSE
audio_miner-0.0.6.dist-info/METADATA
audio_miner-0.0.6.dist-info/WHEEL
audio_miner-0.0.6.dist-info/entry_points.txt
audio_miner-0.0.6.dist-info/top_level.txt
audio_miner-0.0.6.dist-info/RECORD
